monkey_user_manager/__init__.py
monkey_user_manager/server.py
monkey_user_manager-2025.0.0a1.dist-info/licenses/LICENSE
monkey_user_manager-2025.0.0a1.dist-info/METADATA
monkey_user_manager-2025.0.0a1.dist-info/WHEEL
monkey_user_manager-2025.0.0a1.dist-info/top_level.txt
monkey_user_manager-2025.0.0a1.dist-info/RECORD
