Metadata-Version: 2.4
Name: monkey-user-manager
Version: 2025.0.0a1
Summary: A User Manager For Build Server
Author-email: Bigbluemonkey <monkey800_20@qq.com>
License: MIT
Project-URL: Homepage, http://pypi.org
Project-URL: Repository, http://pypi.org
Project-URL: Bug Tracker, http://pypi.org
Keywords: server,database
Classifier: Programming Language :: Python :: 3
Classifier: License :: OSI Approved :: MIT License
Classifier: Operating System :: OS Independent
License-File: LICENSE
Requires-Dist: requests
Requires-Dist: bottle
Dynamic: license-file
